{
  "Frutas y Verduras": [
    {
      "name": "Ver todo",
      "url": "https://www.metro.pe/frutas-y-verduras"
    },
    {
      "name": "Frutas",
      "url": "https://www.metro.pe/frutas-y-verduras/frutas"
    },
    {
      "name": "Verduras",
      "url": "https://www.metro.pe/frutas-y-verduras/verduras"
    }
  ],
  "Carnes, Pollos y Pescados": [
    {
      "name": "Ver todo",
      "url": "https://www.metro.pe/carnes-aves-y-pescados"
    },
    {
      "name": "Premium",
      "url": "https://www.metro.pe/carnes-pollos-y-pescados/premium"
    },
    {
      "name": "Aves y Huevos",
      "url": "https://www.metro.pe/carnes-aves-y-pescados/aves-y-huevos"
    },
    {
      "name": "Cerdo",
      "url": "https://www.metro.pe/carnes-aves-y-pescados/cerdo"
    },
    {
      "name": "Hamburguesas y Apanados",
      "url": "https://www.metro.pe/carnes-aves-y-pescados/hamburguesas-y-apanados"
    },
    {
      "name": "Pescados y Mariscos",
      "url": "https://www.metro.pe/carnes-aves-y-pescados/pescados-y-mariscos"
    },
    {
      "name": "Res y Otras Carnes",
      "url": "https://www.metro.pe/carnes-aves-y-pescados/res-y-otras-carnes"
    },
    {
      "name": "Empanizados de Pescados",
      "url": "https://www.metro.pe/carnes-pollos-y-pescados/empanizados-de-pescados"
    }
  ],
  "Desayuno": [
    {
      "name": "Ver todo",
      "url": "https://www.metro.pe/desayuno"
    },
    {
      "name": "Azúcar y Edulcorantes",
      "url": "https://www.metro.pe/desayuno/azucar-y-edulcorantes"
    },
    {
      "name": "Café e Infusiones",
      "url": "https://www.metro.pe/desayuno/cafe-e-infusiones"
    },
    {
      "name": "Cereales y Avenas",
      "url": "https://www.metro.pe/desayuno/cereales-y-avenas"
    },
    {
      "name": "Mermeladas y Mieles",
      "url": "https://www.metro.pe/desayuno/mermeladas-y-mieles"
    },
    {
      "name": "Modificadores de Leche",
      "url": "https://www.metro.pe/desayuno/modificadores-de-leche"
    },
    {
      "name": "Panes y Tortillas Empacadas",
      "url": "https://www.metro.pe/desayuno/panes-y-tortillas-empacadas"
    },
    {
      "name": "Suplementos Nutricionales para Adultos",
      "url": "https://www.metro.pe/desayuno/suplementos-nutricionales-para-adultos"
    }
  ],
  "Lácteos y Huevos": [
    {
      "name": "Ver todo",
      "url": "https://www.metro.pe/lacteos"
    },
    {
      "name": "La Quesería",
      "url": "https://www.metro.pe/lacteos/la-queseria"
    },
    {
      "name": "Leches",
      "url": "https://www.metro.pe/lacteos/leches"
    },
    {
      "name": "Mantequillas y Margarinas",
      "url": "https://www.metro.pe/lacteos/mantequillas-y-margarinas"
    },
    {
      "name": "Yogures",
      "url": "https://www.metro.pe/lacteos/yogures"
    }
  ],
  "Embutidos y Fiambres": [
    {
      "name": "Ver todo",
      "url": "https://www.metro.pe/embutidos-y-fiambres"
    },
    {
      "name": "Embutidos",
      "url": "https://www.metro.pe/embutidos-y-fiambres/embutidos"
    },
    {
      "name": "Fiambres",
      "url": "https://www.metro.pe/embutidos-y-fiambres/fiambres"
    },
    {
      "name": "Delicatessen",
      "url": "https://www.metro.pe/embutidos-y-fiambres/delicatessen"
    }
  ],
  "Abarrotes": [
    {
      "name": "Ver todo",
      "url": "https://www.metro.pe/abarrotes"
    },
    {
      "name": "Aceites",
      "url": "https://www.metro.pe/abarrotes/aceites"
    },
    {
      "name": "Alimentos en Conserva",
      "url": "https://www.metro.pe/abarrotes/alimentos-en-conserva"
    },
    {
      "name": "Arroz",
      "url": "https://www.metro.pe/abarrotes/arroz"
    },
    {
      "name": "Chocolatería",
      "url": "https://www.metro.pe/abarrotes/chocolateria"
    },
    {
      "name": "Fideos, Pastas y Salsas",
      "url": "https://www.metro.pe/abarrotes/fideos-pastas-y-salsas"
    },
    {
      "name": "Condimentos, Vinagres y Comida Instantánea",
      "url": "https://www.metro.pe/abarrotes/condimentos-vinagres-y-comida-instantanea"
    },
    {
      "name": "Galletas, Snacks y Golosinas",
      "url": "https://www.metro.pe/abarrotes/galletas-snacks-y-golosinas"
    },
    {
      "name": "Menestras",
      "url": "https://www.metro.pe/abarrotes/menestras"
    },
    {
      "name": "Repostería",
      "url": "https://www.metro.pe/abarrotes/reposteria"
    }
  ]
}